<?xml version="1.0" encoding="utf-8" ?><dwsync><file name="index.html" server="ftp.shebar.nyc" local="3570018518" remote="3570012120" Dst="-1" /><file name="main.css" server="ftp.shebar.nyc" local="3570019354" remote="3570012120" Dst="-1" /><file name="index.html" server="ftp.shebar.nyc/public_html/" local="3570018518" remote="3570012360" Dst="-1" /><file name="main.css" server="ftp.shebar.nyc/public_html/" local="3570019354" remote="3570012360" Dst="-1" /><file name="VWzlUwPL.png" server="ftp.shebar.nyc//public_html/" local="3575032279" remote="3575928660" Dst="-1" /><file name="Mobileupdate.jpg" server="ftp.shebar.nyc//public_html/" local="3575032279" remote="3575928660" Dst="-1" /><file name="main.css" server="ftp.shebar.nyc//public_html/" local="3576066646" remote="3576056520" Dst="-1" /><file name="index.html" server="ftp.shebar.nyc//public_html/" local="3576496821" remote="3577226940" Dst="-1" /><file name="bootstrap.jpg" server="ftp.shebar.nyc//public_html/" local="3575032279" remote="3575928780" Dst="-1" /><file name="audiresponsive.mp4" server="ftp.shebar.nyc//public_html/" local="3575032281" remote="3575934120" Dst="-1" /></dwsync>